MANIFEST.in
README.txt
setup.py
docs/HISTORY.txt
docs/HISTORY.txt~
docs/Makefile
docs/conf.py
docs/configure.rst
docs/details.rst
docs/index.rst
docs/intro.rst
docs/_build/doctrees/configure.doctree
docs/_build/doctrees/details.doctree
docs/_build/doctrees/environment.pickle
docs/_build/doctrees/index.doctree
docs/_build/doctrees/intro.doctree
docs/_build/html/.buildinfo
docs/_build/html/configure.html
docs/_build/html/details.html
docs/_build/html/genindex.html
docs/_build/html/index.html
docs/_build/html/intro.html
docs/_build/html/objects.inv
docs/_build/html/search.html
docs/_build/html/searchindex.js
docs/_build/html/_sources/configure.txt
docs/_build/html/_sources/details.txt
docs/_build/html/_sources/index.txt
docs/_build/html/_sources/intro.txt
docs/_build/html/_static/basic.css
docs/_build/html/_static/default.css
docs/_build/html/_static/doctools.js
docs/_build/html/_static/file.png
docs/_build/html/_static/jquery.js
docs/_build/html/_static/minus.png
docs/_build/html/_static/plus.png
docs/_build/html/_static/pygments.css
docs/_build/html/_static/searchtools.js
docs/_build/html/_static/sidebar.js
docs/_build/html/_static/underscore.js
inqbus/__init__.py
inqbus/__init__.pyc
inqbus.bannerrotation.egg-info/PKG-INFO
inqbus.bannerrotation.egg-info/SOURCES.txt
inqbus.bannerrotation.egg-info/dependency_links.txt
inqbus.bannerrotation.egg-info/entry_points.txt
inqbus.bannerrotation.egg-info/namespace_packages.txt
inqbus.bannerrotation.egg-info/not-zip-safe
inqbus.bannerrotation.egg-info/requires.txt
inqbus.bannerrotation.egg-info/top_level.txt
inqbus/bannerrotation/__init__.py
inqbus/bannerrotation/__init__.pyc
inqbus/bannerrotation/configure.zcml
inqbus/bannerrotation/setuphandlers.py
inqbus/bannerrotation/setuphandlers.pyc
inqbus/bannerrotation/browser/__init__.py
inqbus/bannerrotation/browser/__init__.pyc
inqbus/bannerrotation/browser/banner.pt
inqbus/bannerrotation/browser/bannerrotation_config_view.pt
inqbus/bannerrotation/browser/bannerrotation_config_view.py
inqbus/bannerrotation/browser/bannerrotation_config_view.pyc
inqbus/bannerrotation/browser/bannerrotation_config_view.py~
inqbus/bannerrotation/browser/configure.zcml
inqbus/bannerrotation/browser/configure.zcml~
inqbus/bannerrotation/browser/interfaces.py
inqbus/bannerrotation/browser/interfaces.pyc
inqbus/bannerrotation/browser/viewlets.py
