Metadata-Version: 1.0
Name: inqbus.bannerrotation
Version: 1.1
Summary: A simple, ajax based bannerrotation viewlet for plone
Home-page: http://inqbus-hosting.de/community
Author: Max Brauer
Author-email: max.brauer@inqbus.de
License: GPL
Keywords: ajax banner rotation viewlet plone
Platform: UNKNOWN
Classifier: Programming Language :: Python
